{
	"animations": [
		{
			"loop": false,
			"offsets": [
				0,
				0
			],
			"anim": "idle",
			"fps": 24,
			"name": "Pico Idle Dance",
			"indices": []
		},
		{
			"loop": false,
			"offsets": [
				82,
				9
			],
			"anim": "singLEFT",
			"fps": 24,
			"name": "Pico Note Right0",
			"indices": []
		},
		{
			"loop": false,
			"offsets": [
				204,
				-72
			],
			"anim": "singDOWN",
			"fps": 24,
			"name": "Pico Down Note0",
			"indices": []
		},
		{
			"loop": false,
			"offsets": [
				-19,
				25
			],
			"anim": "singUP",
			"fps": 24,
			"name": "pico Up note0",
			"indices": []
		},
		{
			"loop": false,
			"offsets": [
				-59,
				-3
			],
			"anim": "singRIGHT",
			"fps": 24,
			"name": "Pico NOTE LEFT0",
			"indices": []
		}
	],
	"vocals_file": "",
	"no_antialiasing": false,
	"image": "characters/annie_assets",
	"position": [
		-50,
		300
	],
	"healthicon": "annie",
	"flip_x": true,
	"healthbar_colors": [
		255,
		32,
		67
	],
	"camera_position": [
		70,
		-50
	],
	"sing_duration": 4,
	"scale": 1,
	"_editor_isPlayer": false
}